j25ng_cmd/__init__.py
j25ng_cmd/cmd.py
j25ng_cmd-0.2.0.dist-info/METADATA
j25ng_cmd-0.2.0.dist-info/WHEEL
j25ng_cmd-0.2.0.dist-info/entry_points.txt
j25ng_cmd-0.2.0.dist-info/top_level.txt
j25ng_cmd-0.2.0.dist-info/RECORD
