Metadata-Version: 2.1
Name: j25ng_cmd
Version: 0.2.0
Summary: Default template for PDM package
Author-email: j25ng <jsan2861@gmail.com>
License: MIT
Requires-Python: >=3.9
Requires-Dist: j25ng-lotto >=0.2.0
